zensols/util/resources/cleaner.conf
zensols/util/resources/cli-config.conf
zensols/util/resources/cli.conf
zensols/util/resources/default.conf
zensols/util/resources/escape.conf
zensols/cli/__init__.py
zensols/cli/action.py
zensols/cli/app.py
zensols/cli/command.py
zensols/cli/harness.py
zensols/cli/meta.py
zensols/cli/notebook.py
zensols/cli/usage.py
zensols/cli/util.py
zensols/cli/lib/config.py
zensols/cli/lib/log.py
zensols/cli/lib/package.py
zensols/cli/lib/support.py
zensols/config/__init__.py
zensols/config/condyaml.py
zensols/config/configbase.py
zensols/config/configfac.py
zensols/config/dictable.py
zensols/config/dictconfig.py
zensols/config/diff.py
zensols/config/envconfig.py
zensols/config/facbase.py
zensols/config/importfac.py
zensols/config/importini.py
zensols/config/importtree.py
zensols/config/importyaml.py
zensols/config/iniconfig.py
zensols/config/jsonconfig.py
zensols/config/keychain.py
zensols/config/meta.py
zensols/config/serial.py
zensols/config/strconfig.py
zensols/config/treeimpmod.py
zensols/config/writeback.py
zensols/config/yaml.py
zensols/introspect/__init__.py
zensols/introspect/imp.py
zensols/introspect/insp.py
zensols/introspect/intsel.py
zensols/introspect/tester.py
zensols/multi/__init__.py
zensols/multi/factory.py
zensols/multi/stash.py
zensols/persist/__init__.py
zensols/persist/annotation.py
zensols/persist/composite.py
zensols/persist/dealloc.py
zensols/persist/domain.py
zensols/persist/shelve.py
zensols/persist/stash.py
zensols/persist/util.py
zensols/persist/zip.py
zensols/util/__init__.py
zensols/util/clip.py
zensols/util/executor.py
zensols/util/fail.py
zensols/util/hasher.py
zensols/util/log.py
zensols/util/package.py
zensols/util/sci.py
zensols/util/std.py
zensols/util/tempfile.py
zensols/util/time.py
zensols/util/warn.py
zensols/util/writable.py
zensols_util-1.16.3.dist-info/METADATA
zensols_util-1.16.3.dist-info/WHEEL
zensols_util-1.16.3.dist-info/licenses/LICENSE.md
zensols_util-1.16.3.dist-info/RECORD
