Metadata-Version: 2.3
Name: zensols_util
Version: 1.16.3
Summary: Command line, configuration and persistence utilites generally used for any more than basic application.
Project-URL: Homepage, https://github.com/plandes/util
Project-URL: Documentation, https://plandes.github.io/util
Project-URL: Repository, https://github.com/plandes/util.git
Project-URL: Issues, https://github.com/plandes/util/issues
Project-URL: Changelog, https://github.com/plandes/util/blob/master/CHANGELOG.md
Author-email: Paul Landes <landes@mailc.net>
License: MIT
Keywords: tooling,utility
Requires-Python: <3.14,>=3.11
Requires-Dist: configparser~=5.2.0
Requires-Dist: frozendict~=2.4.6
Requires-Dist: packaging~=25.0
Requires-Dist: parse>=1.20.0
Requires-Dist: pip
Requires-Dist: pyyaml~=6.0.1
